discordnotify/__init__.py
discordnotify/app_settings.py
discordnotify/apps.py
discordnotify/auth_hooks.py
discordnotify/core.py
discordnotify/signals.py
discordnotify/tasks.py
discordnotify/urls.py
discordnotify/views.py
discordnotify/migrations/__init__.py
discordnotify/static/discordnotify/discordnotify_logo.png
discordnotify/tests/__init__.py
discordnotify/tests/test_core.py
discordnotify/tests/test_integration.py
aa_discordnotify-3.0.0.dist-info/licenses/LICENSE
aa_discordnotify-3.0.0.dist-info/WHEEL
aa_discordnotify-3.0.0.dist-info/METADATA
aa_discordnotify-3.0.0.dist-info/RECORD
