Metadata-Version: 2.4
Name: aa-discordnotify
Version: 3.0.0
Summary: Forward Alliance Auth notifications to users on Discord.
Author-email: Erik Kalkoken <kalkoken87@gmail.com>
Requires-Python: >=3.8
Classifier: Environment :: Web Environment
Classifier: Framework :: Django
Classifier: Framework :: Django :: 4.2
Classifier: Intended Audience :: Developers
Classifier: License :: OSI Approved :: MIT License
Classifier: Operating System :: OS Independent
Classifier: Programming Language :: Python
Classifier: Programming Language :: Python :: 3.8
Classifier: Programming Language :: Python :: 3.9
Classifier: Programming Language :: Python :: 3.10
Classifier: Programming Language :: Python :: 3.11
Classifier: Programming Language :: Python :: 3.12
Classifier: Topic :: Internet :: WWW/HTTP
Classifier: Topic :: Internet :: WWW/HTTP :: Dynamic Content
License-File: LICENSE
Requires-Dist: allianceauth-app-utils>=1.19
Requires-Dist: allianceauth>=4,<5
Requires-Dist: discordproxy>=1.4.0
Project-URL: Changelog, https://gitlab.com/ErikKalkoken/aa-discordnotify/-/blob/master/CHANGELOG.md
Project-URL: Homepage, https://gitlab.com/ErikKalkoken/aa-discordnotify
Project-URL: Source, https://gitlab.com/ErikKalkoken/aa-discordnotify
Project-URL: Tracker, https://gitlab.com/ErikKalkoken/aa-discordnotify/-/issues
